{
  "typography": {
    "heading": {
      "2xl": {
        "$type": "typography",
        "$value": {
          "fontFamily": "{font.family}",
          "fontWeight": "{font-weight.medium}",
          "lineHeight": "{line-height.sm}",
          "fontSize": "{font-size.11}",
          "letterSpacing": "{letter-spacing.1}"
        }
      },
      "xl": {
        "$type": "typography",
        "$value": {
          "fontFamily": "{font.family}",
          "fontWeight": "{font-weight.medium}",
          "lineHeight": "{line-height.sm}",
          "fontSize": "{font-size.10}",
          "letterSpacing": "{letter-spacing.1}"
        }
      },
      "lg": {
        "$type": "typography",
        "$value": {
          "fontFamily": "{font.family}",
          "fontWeight": "{font-weight.medium}",
          "lineHeight": "{line-height.sm}",
          "fontSize": "{font-size.9}",
          "letterSpacing": "{letter-spacing.2}"
        }
      },
      "md": {
        "$type": "typography",
        "$value": {
          "fontFamily": "{font.family}",
          "fontWeight": "{font-weight.medium}",
          "lineHeight": "{line-height.sm}",
          "fontSize": "{font-size.8}",
          "letterSpacing": "{letter-spacing.3}"
        }
      },
      "sm": {
        "$type": "typography",
        "$value": {
          "fontFamily": "{font.family}",
          "fontWeight": "{font-weight.medium}",
          "lineHeight": "{line-height.sm}",
          "fontSize": "{font-size.7}",
          "letterSpacing": "{letter-spacing.5}"
        }
      },
      "xs": {
        "$type": "typography",
        "$value": {
          "fontFamily": "{font.family}",
          "fontWeight": "{font-weight.medium}",
          "lineHeight": "{line-height.sm}",
          "fontSize": "{font-size.6}",
          "letterSpacing": "{letter-spacing.6}"
        }
      },
      "2xs": {
        "$type": "typography",
        "$value": {
          "fontFamily": "{font.family}",
          "fontWeight": "{font-weight.medium}",
          "lineHeight": "{line-height.sm}",
          "fontSize": "{font-size.5}",
          "letterSpacing": "{letter-spacing.6}"
        }
      }
    },
    "body": {
      "xl": {
        "$type": "typography",
        "$value": {
          "fontFamily": "{font.family}",
          "fontWeight": "{font-weight.regular}",
          "lineHeight": "{line-height.md}",
          "fontSize": "{font-size.7}",
          "letterSpacing": "{letter-spacing.8}"
        }
      },
      "lg": {
        "$type": "typography",
        "$value": {
          "fontFamily": "{font.family}",
          "fontWeight": "{font-weight.regular}",
          "lineHeight": "{line-height.md}",
          "fontSize": "{font-size.6}",
          "letterSpacing": "{letter-spacing.8}"
        }
      },
      "md": {
        "$type": "typography",
        "$value": {
          "fontFamily": "{font.family}",
          "fontWeight": "{font-weight.regular}",
          "lineHeight": "{line-height.md}",
          "fontSize": "{font-size.5}",
          "letterSpacing": "{letter-spacing.8}"
        }
      },
      "sm": {
        "$type": "typography",
        "$value": {
          "fontFamily": "{font.family}",
          "fontWeight": "{font-weight.regular}",
          "lineHeight": "{line-height.md}",
          "fontSize": "{font-size.4}",
          "letterSpacing": "{letter-spacing.7}"
        }
      },
      "xs": {
        "$type": "typography",
        "$value": {
          "fontFamily": "{font.family}",
          "fontWeight": "{font-weight.regular}",
          "lineHeight": "{line-height.md}",
          "fontSize": "{font-size.3}",
          "letterSpacing": "{letter-spacing.6}"
        }
      },
      "short": {
        "xl": {
          "$type": "typography",
          "$value": {
            "fontFamily": "{font.family}",
            "fontWeight": "{font-weight.regular}",
            "lineHeight": "{line-height.sm}",
            "fontSize": "{font-size.7}",
            "letterSpacing": "{letter-spacing.8}"
          }
        },
        "lg": {
          "$type": "typography",
          "$value": {
            "fontFamily": "{font.family}",
            "fontWeight": "{font-weight.regular}",
            "lineHeight": "{line-height.sm}",
            "fontSize": "{font-size.6}",
            "letterSpacing": "{letter-spacing.8}"
          }
        },
        "md": {
          "$type": "typography",
          "$value": {
            "fontFamily": "{font.family}",
            "fontWeight": "{font-weight.regular}",
            "lineHeight": "{line-height.sm}",
            "fontSize": "{font-size.5}",
            "letterSpacing": "{letter-spacing.8}"
          }
        },
        "sm": {
          "$type": "typography",
          "$value": {
            "fontFamily": "{font.family}",
            "fontWeight": "{font-weight.regular}",
            "lineHeight": "{line-height.sm}",
            "fontSize": "{font-size.4}",
            "letterSpacing": "{letter-spacing.7}"
          }
        },
        "xs": {
          "$type": "typography",
          "$value": {
            "fontFamily": "{font.family}",
            "fontWeight": "{font-weight.regular}",
            "lineHeight": "{line-height.sm}",
            "fontSize": "{font-size.3}",
            "letterSpacing": "{letter-spacing.6}"
          }
        }
      },
      "long": {
        "xl": {
          "$type": "typography",
          "$value": {
            "fontFamily": "{font.family}",
            "fontWeight": "{font-weight.regular}",
            "lineHeight": "{line-height.lg}",
            "fontSize": "{font-size.7}",
            "letterSpacing": "{letter-spacing.8}"
          }
        },
        "lg": {
          "$type": "typography",
          "$value": {
            "fontFamily": "{font.family}",
            "fontWeight": "{font-weight.regular}",
            "lineHeight": "{line-height.lg}",
            "fontSize": "{font-size.6}",
            "letterSpacing": "{letter-spacing.8}"
          }
        },
        "md": {
          "$type": "typography",
          "$value": {
            "fontFamily": "{font.family}",
            "fontWeight": "{font-weight.regular}",
            "lineHeight": "{line-height.lg}",
            "fontSize": "{font-size.5}",
            "letterSpacing": "{letter-spacing.8}"
          }
        },
        "sm": {
          "$type": "typography",
          "$value": {
            "fontFamily": "{font.family}",
            "fontWeight": "{font-weight.regular}",
            "lineHeight": "{line-height.lg}",
            "fontSize": "{font-size.4}",
            "letterSpacing": "{letter-spacing.7}"
          }
        },
        "xs": {
          "$type": "typography",
          "$value": {
            "fontFamily": "{font.family}",
            "fontWeight": "{font-weight.regular}",
            "lineHeight": "{line-height.lg}",
            "fontSize": "{font-size.3}",
            "letterSpacing": "{letter-spacing.6}"
          }
        }
      }
    }
  },
  "disabled": {
    "opacity": {
      "$type": "opacity",
      "$value": "{opacity.30}"
    }
  },
  "border-radius": {
    "sm": {
      "$type": "borderRadius",
      "$value": "{border-radius.1}"
    },
    "md": {
      "$type": "borderRadius",
      "$value": "{border-radius.2}"
    },
    "lg": {
      "$type": "borderRadius",
      "$value": "{border-radius.3}"
    },
    "xl": {
      "$type": "borderRadius",
      "$value": "{border-radius.4}"
    },
    "default": {
      "$type": "borderRadius",
      "$value": "{border-radius.5}"
    },
    "full": {
      "$type": "borderRadius",
      "$value": "{border-radius.6}"
    }
  },
  "border-width": {
    "default": {
      "$type": "borderWidth",
      "$value": "{border-width.1}"
    },
    "highlight": {
      "$type": "borderWidth",
      "$value": "{border-width.2}"
    }
  },
  "shadow": {
    "xs": {
      "$type": "boxShadow",
      "$value": "{shadow.100}"
    },
    "sm": {
      "$type": "boxShadow",
      "$value": "{shadow.200}"
    },
    "md": {
      "$type": "boxShadow",
      "$value": "{shadow.300}"
    },
    "lg": {
      "$type": "boxShadow",
      "$value": "{shadow.400}"
    },
    "xl": {
      "$type": "boxShadow",
      "$value": "{shadow.500}"
    }
  }
}
