{
  "textCase": {
    "none": {
      "value": "none",
      "type": "textCase"
    }
  },
  "textDecoration": {
    "none": {
      "value": "none",
      "type": "textDecoration"
    },
    "underline": {
      "value": "underline",
      "type": "textDecoration"
    }
  },
  "font-static": {
    "small": {
      "value": "16",
      "type": "fontSizes"
    },
    "medium": {
      "value": "18",
      "type": "fontSizes"
    },
    "large": {
      "value": "24",
      "type": "fontSizes"
    }
  },
  "lineHeights": {
    "300": {
      "value": "130%",
      "type": "lineHeights"
    },
    "500": {
      "value": "150%",
      "type": "lineHeights"
    },
    "600": {
      "value": "160%",
      "type": "lineHeights"
    },
    "700": {
      "value": "170%",
      "type": "lineHeights"
    }
  },
  "fontWeights": {
    "medium": {
      "value": "500",
      "type": "fontWeights"
    },
    "semibold": {
      "value": "600",
      "type": "fontWeights"
    },
    "regular": {
      "value": "400",
      "type": "fontWeights"
    }
  },
  "border_width": {
    "1": {
      "value": "1px",
      "type": "borderWidth"
    },
    "2": {
      "value": "2px",
      "type": "borderWidth"
    }
  },
  "shadow": {
    "100": {
      "value": [
        {
          "color": "rgba(0,0,0,0.16)",
          "type": "dropShadow",
          "x": "0",
          "y": "0",
          "blur": "1",
          "spread": "0"
        },
        {
          "x": "0",
          "y": "1",
          "blur": "2",
          "spread": "0",
          "color": "rgba(0,0,0,0.12)",
          "type": "dropShadow"
        }
      ],
      "type": "boxShadow"
    },
    "200": {
      "value": [
        {
          "color": "rgba(0,0,0,0.15)",
          "type": "dropShadow",
          "x": "0",
          "y": "0",
          "blur": "1",
          "spread": "0"
        },
        {
          "color": "rgba(0,0,0,0.12)",
          "type": "dropShadow",
          "x": "0",
          "y": "1",
          "blur": "2",
          "spread": "0"
        },
        {
          "x": "0",
          "y": "2",
          "blur": "4",
          "spread": "0",
          "color": "rgba(0,0,0,0.1)",
          "type": "dropShadow"
        }
      ],
      "type": "boxShadow"
    },
    "300": {
      "value": [
        {
          "color": "rgba(0,0,0,0.14)",
          "type": "dropShadow",
          "x": "0",
          "y": "0",
          "blur": "1",
          "spread": "0"
        },
        {
          "color": "rgba(0,0,0,0.12)",
          "type": "dropShadow",
          "x": "0",
          "y": "2",
          "blur": "4",
          "spread": "0"
        },
        {
          "x": "0",
          "y": "4",
          "blur": "8",
          "spread": "0",
          "color": "rgba(0,0,0,0.12)",
          "type": "dropShadow"
        }
      ],
      "type": "boxShadow"
    },
    "400": {
      "value": [
        {
          "color": "rgba(0,0,0,0.13)",
          "type": "dropShadow",
          "x": "0",
          "y": "0",
          "blur": "1",
          "spread": "0"
        },
        {
          "color": "rgba(0,0,0,0.13)",
          "type": "dropShadow",
          "x": "0",
          "y": "3",
          "blur": "5",
          "spread": "0"
        },
        {
          "x": "0",
          "y": "6",
          "blur": "12",
          "spread": "0",
          "color": "rgba(0,0,0,0.14)",
          "type": "dropShadow"
        }
      ],
      "type": "boxShadow"
    },
    "500": {
      "value": [
        {
          "color": "rgba(0,0,0,0.12)",
          "type": "dropShadow",
          "x": "0",
          "y": "0",
          "blur": "1",
          "spread": "0"
        },
        {
          "color": "rgba(0,0,0,0.16)",
          "type": "dropShadow",
          "x": "0",
          "y": "4",
          "blur": "8",
          "spread": "0"
        },
        {
          "x": "0",
          "y": "12",
          "blur": "24",
          "spread": "0",
          "color": "rgba(0,0,0,0.16)",
          "type": "dropShadow"
        }
      ],
      "type": "boxShadow"
    }
  },
  "font-size": {
    "f-3": {
      "value": "12",
      "type": "fontSizes"
    },
    "f-2": {
      "value": "13",
      "type": "fontSizes"
    },
    "f-1": {
      "value": "14",
      "type": "fontSizes"
    },
    "f0": {
      "value": "16",
      "type": "fontSizes"
    },
    "f1": {
      "value": "18",
      "type": "fontSizes"
    },
    "f2": {
      "value": "21",
      "type": "fontSizes"
    },
    "f3": {
      "value": "24",
      "type": "fontSizes"
    },
    "f4": {
      "value": "30",
      "type": "fontSizes"
    },
    "f5": {
      "value": "36",
      "type": "fontSizes"
    },
    "f6": {
      "value": "48",
      "type": "fontSizes"
    },
    "f7": {
      "value": "60",
      "type": "fontSizes"
    }
  },
  "borderRadius": {
    "sm": {
      "value": "2",
      "type": "borderRadius"
    },
    "md": {
      "value": "4",
      "type": "borderRadius"
    },
    "lg": {
      "value": "8",
      "type": "borderRadius"
    },
    "xl": {
      "value": "12",
      "type": "borderRadius"
    },
    "2xl": {
      "value": "16",
      "type": "borderRadius"
    },
    "3xl": {
      "value": "24",
      "type": "borderRadius"
    },
    "4xl": {
      "value": "32",
      "type": "borderRadius"
    },
    "full": {
      "value": "9999",
      "type": "borderRadius"
    }
  },
  "opacity": {
    "disabledComponents": {
      "value": "30%",
      "type": "opacity"
    }
  }
}