{
  "digdir": {
    "accent": {
      "1": {
        "$type": "color",
        "$value": "#ffffff"
      },
      "2": {
        "$type": "color",
        "$value": "#eef4fa"
      },
      "3": {
        "$type": "color",
        "$value": "#ffffff"
      },
      "4": {
        "$type": "color",
        "$value": "#ddeaf6"
      },
      "5": {
        "$type": "color",
        "$value": "#c7ddf0"
      },
      "6": {
        "$type": "color",
        "$value": "#afcee9"
      },
      "7": {
        "$type": "color",
        "$value": "#99c0e3"
      },
      "8": {
        "$type": "color",
        "$value": "#2a7cc5"
      },
      "9": {
        "$type": "color",
        "$value": "#005db1"
      },
      "10": {
        "$type": "color",
        "$value": "#005db1"
      },
      "11": {
        "$type": "color",
        "$value": "#002c54"
      },
      "12": {
        "$type": "color",
        "$value": "#0062BA"
      },
      "13": {
        "$type": "color",
        "$value": "#004f96"
      },
      "14": {
        "$type": "color",
        "$value": "#003d75"
      },
      "15": {
        "$type": "color",
        "$value": "#dbe9f5"
      },
      "16": {
        "$type": "color",
        "$value": "#ffffff"
      }
    },
    "brand1": {
      "1": {
        "$type": "color",
        "$value": "#ffffff"
      },
      "2": {
        "$type": "color",
        "$value": "#fef0f1"
      },
      "3": {
        "$type": "color",
        "$value": "#ffffff"
      },
      "4": {
        "$type": "color",
        "$value": "#fde2e3"
      },
      "5": {
        "$type": "color",
        "$value": "#fccfd1"
      },
      "6": {
        "$type": "color",
        "$value": "#fababc"
      },
      "7": {
        "$type": "color",
        "$value": "#f9a5a8"
      },
      "8": {
        "$type": "color",
        "$value": "#cb4f53"
      },
      "9": {
        "$type": "color",
        "$value": "#9e3d40"
      },
      "10": {
        "$type": "color",
        "$value": "#9e3d40"
      },
      "11": {
        "$type": "color",
        "$value": "#4b1d1e"
      },
      "12": {
        "$type": "color",
        "$value": "#F45F63"
      },
      "13": {
        "$type": "color",
        "$value": "#f78588"
      },
      "14": {
        "$type": "color",
        "$value": "#f9a6a8"
      },
      "15": {
        "$type": "color",
        "$value": "#020101"
      },
      "16": {
        "$type": "color",
        "$value": "#000000"
      }
    },
    "brand2": {
      "1": {
        "$type": "color",
        "$value": "#ffffff"
      },
      "2": {
        "$type": "color",
        "$value": "#fbf3df"
      },
      "3": {
        "$type": "color",
        "$value": "#ffffff"
      },
      "4": {
        "$type": "color",
        "$value": "#f8e7c1"
      },
      "5": {
        "$type": "color",
        "$value": "#f3d797"
      },
      "6": {
        "$type": "color",
        "$value": "#edc567"
      },
      "7": {
        "$type": "color",
        "$value": "#e8b43a"
      },
      "8": {
        "$type": "color",
        "$value": "#9a7216"
      },
      "9": {
        "$type": "color",
        "$value": "#775811"
      },
      "10": {
        "$type": "color",
        "$value": "#775811"
      },
      "11": {
        "$type": "color",
        "$value": "#382908"
      },
      "12": {
        "$type": "color",
        "$value": "#E5AA20"
      },
      "13": {
        "$type": "color",
        "$value": "#c9951c"
      },
      "14": {
        "$type": "color",
        "$value": "#af8218"
      },
      "15": {
        "$type": "color",
        "$value": "#2c2006"
      },
      "16": {
        "$type": "color",
        "$value": "#000000"
      }
    },
    "brand3": {
      "1": {
        "$type": "color",
        "$value": "#ffffff"
      },
      "2": {
        "$type": "color",
        "$value": "#eaf5fe"
      },
      "3": {
        "$type": "color",
        "$value": "#ffffff"
      },
      "4": {
        "$type": "color",
        "$value": "#d5ecfd"
      },
      "5": {
        "$type": "color",
        "$value": "#b9dffc"
      },
      "6": {
        "$type": "color",
        "$value": "#99d0fa"
      },
      "7": {
        "$type": "color",
        "$value": "#7bc3f9"
      },
      "8": {
        "$type": "color",
        "$value": "#197dc9"
      },
      "9": {
        "$type": "color",
        "$value": "#13619c"
      },
      "10": {
        "$type": "color",
        "$value": "#13619c"
      },
      "11": {
        "$type": "color",
        "$value": "#092d49"
      },
      "12": {
        "$type": "color",
        "$value": "#1E98F5"
      },
      "13": {
        "$type": "color",
        "$value": "#53b0f7"
      },
      "14": {
        "$type": "color",
        "$value": "#81c5f9"
      },
      "15": {
        "$type": "color",
        "$value": "#010507"
      },
      "16": {
        "$type": "color",
        "$value": "#000000"
      }
    },
    "neutral": {
      "1": {
        "$type": "color",
        "$value": "#ffffff"
      },
      "2": {
        "$type": "color",
        "$value": "#f3f4f4"
      },
      "3": {
        "$type": "color",
        "$value": "#ffffff"
      },
      "4": {
        "$type": "color",
        "$value": "#e7e9ea"
      },
      "5": {
        "$type": "color",
        "$value": "#d8dadd"
      },
      "6": {
        "$type": "color",
        "$value": "#c7cacf"
      },
      "7": {
        "$type": "color",
        "$value": "#b8bcc1"
      },
      "8": {
        "$type": "color",
        "$value": "#717a84"
      },
      "9": {
        "$type": "color",
        "$value": "#545e6b"
      },
      "10": {
        "$type": "color",
        "$value": "#545e6b"
      },
      "11": {
        "$type": "color",
        "$value": "#1f2c3d"
      },
      "12": {
        "$type": "color",
        "$value": "#1E2B3C"
      },
      "13": {
        "$type": "color",
        "$value": "#313d4d"
      },
      "14": {
        "$type": "color",
        "$value": "#444f5d"
      },
      "15": {
        "$type": "color",
        "$value": "#babec4"
      },
      "16": {
        "$type": "color",
        "$value": "#ffffff"
      }
    },
    "info": {
      "1": {
        "$type": "color",
        "$value": "#ffffff"
      },
      "2": {
        "$type": "color",
        "$value": "#edf5fa"
      },
      "3": {
        "$type": "color",
        "$value": "#ffffff"
      },
      "4": {
        "$type": "color",
        "$value": "#dcebf6"
      },
      "5": {
        "$type": "color",
        "$value": "#c5ddf0"
      },
      "6": {
        "$type": "color",
        "$value": "#abcfe9"
      },
      "7": {
        "$type": "color",
        "$value": "#94c1e3"
      },
      "8": {
        "$type": "color",
        "$value": "#1f7dc5"
      },
      "9": {
        "$type": "color",
        "$value": "#0860a3"
      },
      "10": {
        "$type": "color",
        "$value": "#0860a3"
      },
      "11": {
        "$type": "color",
        "$value": "#042d4d"
      },
      "12": {
        "$type": "color",
        "$value": "#0A71C0"
      },
      "13": {
        "$type": "color",
        "$value": "#085d9f"
      },
      "14": {
        "$type": "color",
        "$value": "#074a7e"
      },
      "15": {
        "$type": "color",
        "$value": "#eff6fb"
      },
      "16": {
        "$type": "color",
        "$value": "#ffffff"
      }
    },
    "success": {
      "1": {
        "$type": "color",
        "$value": "#ffffff"
      },
      "2": {
        "$type": "color",
        "$value": "#ecf6ee"
      },
      "3": {
        "$type": "color",
        "$value": "#ffffff"
      },
      "4": {
        "$type": "color",
        "$value": "#daeddd"
      },
      "5": {
        "$type": "color",
        "$value": "#c3e2c7"
      },
      "6": {
        "$type": "color",
        "$value": "#a8d5ae"
      },
      "7": {
        "$type": "color",
        "$value": "#8fc997"
      },
      "8": {
        "$type": "color",
        "$value": "#108c22"
      },
      "9": {
        "$type": "color",
        "$value": "#056d13"
      },
      "10": {
        "$type": "color",
        "$value": "#056d13"
      },
      "11": {
        "$type": "color",
        "$value": "#023409"
      },
      "12": {
        "$type": "color",
        "$value": "#068718"
      },
      "13": {
        "$type": "color",
        "$value": "#057014"
      },
      "14": {
        "$type": "color",
        "$value": "#045a10"
      },
      "15": {
        "$type": "color",
        "$value": "#fafdfb"
      },
      "16": {
        "$type": "color",
        "$value": "#ffffff"
      }
    },
    "warning": {
      "1": {
        "$type": "color",
        "$value": "#ffffff"
      },
      "2": {
        "$type": "color",
        "$value": "#fcf2e2"
      },
      "3": {
        "$type": "color",
        "$value": "#ffffff"
      },
      "4": {
        "$type": "color",
        "$value": "#fae6c6"
      },
      "5": {
        "$type": "color",
        "$value": "#f6d5a0"
      },
      "6": {
        "$type": "color",
        "$value": "#f2c275"
      },
      "7": {
        "$type": "color",
        "$value": "#eeb04c"
      },
      "8": {
        "$type": "color",
        "$value": "#a56d13"
      },
      "9": {
        "$type": "color",
        "$value": "#80540f"
      },
      "10": {
        "$type": "color",
        "$value": "#80540f"
      },
      "11": {
        "$type": "color",
        "$value": "#3c2807"
      },
      "12": {
        "$type": "color",
        "$value": "#EA9B1B"
      },
      "13": {
        "$type": "color",
        "$value": "#cd8818"
      },
      "14": {
        "$type": "color",
        "$value": "#b27614"
      },
      "15": {
        "$type": "color",
        "$value": "#271a04"
      },
      "16": {
        "$type": "color",
        "$value": "#000000"
      }
    },
    "danger": {
      "1": {
        "$type": "color",
        "$value": "#ffffff"
      },
      "2": {
        "$type": "color",
        "$value": "#fbf1f1"
      },
      "3": {
        "$type": "color",
        "$value": "#ffffff"
      },
      "4": {
        "$type": "color",
        "$value": "#f8e4e4"
      },
      "5": {
        "$type": "color",
        "$value": "#f3d2d2"
      },
      "6": {
        "$type": "color",
        "$value": "#edbfbf"
      },
      "7": {
        "$type": "color",
        "$value": "#e8adad"
      },
      "8": {
        "$type": "color",
        "$value": "#ce4d4d"
      },
      "9": {
        "$type": "color",
        "$value": "#b81a1a"
      },
      "10": {
        "$type": "color",
        "$value": "#b81a1a"
      },
      "11": {
        "$type": "color",
        "$value": "#590d0d"
      },
      "12": {
        "$type": "color",
        "$value": "#C01B1B"
      },
      "13": {
        "$type": "color",
        "$value": "#9b1616"
      },
      "14": {
        "$type": "color",
        "$value": "#791111"
      },
      "15": {
        "$type": "color",
        "$value": "#f7e1e1"
      },
      "16": {
        "$type": "color",
        "$value": "#ffffff"
      }
    },
    "link": {
      "visited": {
        "$type": "color",
        "$value": "#663299"
      }
    },
    "focus": {
      "inner": {
        "$type": "color",
        "$value": "#ffffff"
      },
      "outer": {
        "$type": "color",
        "$value": "#1f2c3d"
      }
    }
  }
}